llm_img_cat/__init__.py
llm_img_cat/categorizer.py
llm_img_cat-0.1.2.dist-info/METADATA
llm_img_cat-0.1.2.dist-info/WHEEL
llm_img_cat-0.1.2.dist-info/entry_points.txt
llm_img_cat-0.1.2.dist-info/top_level.txt
llm_img_cat-0.1.2.dist-info/RECORD
