Metadata-Version: 2.1
Name: llm-img-cat
Version: 0.1.2
Summary: LLM-based image categorization tool with focus on book cover detection
Home-page: https://github.com/clava-ai/llm_image_categorizator
Author: Clava Team
Author-email: team@clava.ai
Project-URL: Bug Tracker, https://github.com/clava-ai/llm_image_categorizator/issues
Project-URL: Documentation, https://github.com/clava-ai/llm_image_categorizator/docs
Project-URL: Source Code, https://github.com/clava-ai/llm_image_categorizator
Keywords: llm,image,categorization,ai,book cover,vision,machine learning
Classifier: Development Status :: 3 - Alpha
Classifier: Intended Audience :: Developers
Classifier: Intended Audience :: Science/Research
Classifier: License :: OSI Approved :: MIT License
Classifier: Programming Language :: Python :: 3
Classifier: Programming Language :: Python :: 3.9
Classifier: Programming Language :: Python :: 3.10
Classifier: Programming Language :: Python :: 3.11
Classifier: Topic :: Scientific/Engineering :: Artificial Intelligence
Classifier: Topic :: Scientific/Engineering :: Image Recognition
Requires-Python: >=3.9
Requires-Dist: python-dotenv>=1.0.0
Requires-Dist: pyyaml>=6.0.1
Requires-Dist: requests>=2.31.0
Requires-Dist: pillow>=10.0.0
Requires-Dist: numpy>=1.24.0
Requires-Dist: imagehash>=4.3.0
Requires-Dist: responses>=0.25.0
Requires-Dist: psutil>=5.9.0
Requires-Dist: rich>=13.7.0
Requires-Dist: openai>=1.0.0
Requires-Dist: anthropic>=0.5.0
Requires-Dist: dashscope>=1.10.0
Requires-Dist: google-generativeai==0.1.0rc1
Requires-Dist: python-magic>=0.4.27
Requires-Dist: tenacity>=8.2.3
Requires-Dist: cachetools>=5.3.1
Requires-Dist: typing-extensions>=4.8.0
Requires-Dist: pytest>=7.0.0
Requires-Dist: pytest-asyncio>=0.21.0
Requires-Dist: pytest-cov>=4.1.0
Requires-Dist: pytest-random-order==1.1.0
Requires-Dist: matplotlib>=3.7.0
Provides-Extra: dev
Requires-Dist: black>=23.0.0; extra == "dev"
Requires-Dist: isort>=5.12.0; extra == "dev"
Requires-Dist: flake8>=6.0.0; extra == "dev"
Requires-Dist: mypy>=1.5.0; extra == "dev"
Requires-Dist: pytest>=7.0.0; extra == "dev"
Requires-Dist: pytest-asyncio>=0.21.0; extra == "dev"
Requires-Dist: pytest-cov>=4.1.0; extra == "dev"
Requires-Dist: pytest-random-order==1.1.0; extra == "dev"
Provides-Extra: docs
Requires-Dist: mkdocs>=1.5.0; extra == "docs"
Requires-Dist: mkdocs-material>=9.0.0; extra == "docs"
Requires-Dist: pdoc3>=0.10.0; extra == "docs"
Provides-Extra: examples
Requires-Dist: matplotlib>=3.7.0; extra == "examples"
Requires-Dist: jupyter>=1.0.0; extra == "examples"
